cloudwatch_alarms_to_teams/__init__.py
cloudwatch_alarms_to_teams/py.typed
cloudwatch_alarms_to_teams/_jsii/__init__.py
cloudwatch_alarms_to_teams/_jsii/cloudwatch-alarms-to-teams@0.1.13.jsii.tgz
cloudwatch_alarms_to_teams-0.1.13.dist-info/LICENSE
cloudwatch_alarms_to_teams-0.1.13.dist-info/METADATA
cloudwatch_alarms_to_teams-0.1.13.dist-info/WHEEL
cloudwatch_alarms_to_teams-0.1.13.dist-info/top_level.txt
cloudwatch_alarms_to_teams-0.1.13.dist-info/RECORD
