Metadata-Version: 2.1
Name: cloudwatch-alarms-to-teams
Version: 0.1.13
Summary: cloudwatch-alarms-to-teams
Home-page: https://github.com/1davidmichael/Cloudwatch-Alarms-to-Chat-Platforms
Author: David Michael<1.david.michael@gmail.com>
License: Apache-2.0
Project-URL: Source, https://github.com/1davidmichael/Cloudwatch-Alarms-to-Chat-Platforms
Platform: UNKNOWN
Classifier: Intended Audience :: Developers
Classifier: Operating System :: OS Independent
Classifier: Programming Language :: JavaScript
Classifier: Programming Language :: Python :: 3 :: Only
Classifier: Programming Language :: Python :: 3.6
Classifier: Programming Language :: Python :: 3.7
Classifier: Programming Language :: Python :: 3.8
Classifier: Programming Language :: Python :: 3.9
Classifier: Typing :: Typed
Classifier: Development Status :: 5 - Production/Stable
Classifier: License :: OSI Approved
Requires-Python: >=3.6
Requires-Dist: aws-cdk.aws-cloudwatch-actions (<2.0.0,>=1.114.0)
Requires-Dist: aws-cdk.aws-cloudwatch (<2.0.0,>=1.114.0)
Requires-Dist: aws-cdk.aws-lambda-event-sources (<2.0.0,>=1.114.0)
Requires-Dist: aws-cdk.aws-lambda-nodejs (<2.0.0,>=1.114.0)
Requires-Dist: aws-cdk.aws-lambda (<2.0.0,>=1.114.0)
Requires-Dist: aws-cdk.aws-sns (<2.0.0,>=1.114.0)
Requires-Dist: aws-cdk.core (<2.0.0,>=1.114.0)
Requires-Dist: constructs (<4.0.0,>=3.2.27)
Requires-Dist: jsii (<2.0.0,>=1.31.0)
Requires-Dist: publication (>=0.0.3)
